mcbs/__init__.py
mcbs/benchmarker/__init__.py
mcbs/benchmarker/benchmarker.py
mcbs/benchmarking/__init__.py
mcbs/benchmarking/benchmark.py
mcbs/datasets/__init__.py
mcbs/datasets/dataset_loader.py
mcbs/datasets/metadata.json
mcbs/models/__init__.py
mcbs/models/base.py
mcbs/models/ltds_model copy.py
mcbs/models/ltds_model.py
mcbs/models/modecanada_model copy.py
mcbs/models/modecanada_model.py
mcbs/models/swissmetro_model.py
mcbs/models/swissmetro_model_backup.py
mcbs/utils/__init__.py
mcbs/utils/biogeme_wrapper.py
mcbs/utils/individual_parameters.py
mcbs/utils/metrics.py
mcbs-0.1.2.dist-info/licenses/LICENSE
mcbs-0.1.2.dist-info/METADATA
mcbs-0.1.2.dist-info/WHEEL
mcbs-0.1.2.dist-info/top_level.txt
mcbs-0.1.2.dist-info/RECORD
